NetDes/NetDes.py
NetDes/__init__.py
netdes-1.0.6.dist-info/licenses/LICENSE.txt
netdes-1.0.6.dist-info/METADATA
netdes-1.0.6.dist-info/WHEEL
netdes-1.0.6.dist-info/top_level.txt
netdes-1.0.6.dist-info/RECORD
