Metadata-Version: 2.4
Name: NetDes
Version: 1.0.6
Summary: Network modeling based on dynamic equation simulation (NetDes)
Home-page: https://github.com/lusystemsbio/NetDes
Download-URL: https://github.com/lusystemsbio/NetDes/archive/refs/heads/main.zip
Author: Yukai You
Author-email: you.yu@northeastern.edu
License: MIT
Keywords: NetDes,TF,ODE,GRN,trajectories
Classifier: Programming Language :: Python :: 3
Classifier: License :: OSI Approved :: MIT License
Classifier: Operating System :: OS Independent
Requires-Python: >=3.9
License-File: LICENSE.txt
Requires-Dist: numpy>=1.26.4
Requires-Dist: torch>=1.12.1
Requires-Dist: matplotlib>=3.5.1
Requires-Dist: pandas>=2.2.2
Requires-Dist: scipy>=1.13.1
Requires-Dist: scikit-learn>=1.0.2
Dynamic: author
Dynamic: author-email
Dynamic: classifier
Dynamic: description
Dynamic: description-content-type
Dynamic: download-url
Dynamic: home-page
Dynamic: keywords
Dynamic: license
Dynamic: license-file
Dynamic: requires-dist
Dynamic: requires-python
Dynamic: summary
